[{"event_type": "stage_end", "appData": {"ToolsClicked": "[]", "MissionsCompleted": [0, 0, 0, 0], "CurrentLevel": "", "CurrentMission": "Mission 1", "CaseDetails": ["exactly5emptysides", ["fig027", "fig031", "fig014", "fig058", null, null, null, null], ["The culprit has less than 6 straight sides"], ["Incorrect"]], "scoreAchieved": 30, "GlossaryDownloaded": false, "MissionsPlayed": [1, 0, 0, 0], "starEarned": 0, "NumberOfClues": "", "StagePlayed": 1, "ReplayUsedNumber": 0, "CorrectRelease": "[]", "TimeSpentStage": "0:3:10", "starTotal": 0, "IncorrectRelease": "[{\"clue\":1,\"fig\":[\"fig027\",\"fig031\",\"fig014\"]}]", "statusConpleted": "failed", "StorySkiped": true, "highScore": 30, "HyperlinksClicked": "[]", "NumberOfErrors": ""}, "appName": "policesquad", "userId": "28372", "language": "en", "sessionId": "xuj375mwwicylymmx00xkub00bz9mkle", "buddyIds": "", "createdAt": "2018-10-30 12:44:36"}, {"event_type": "stage_end", "language": "en", "appName": "policesquad", "userId": "28372", "sessionId": "xuj375mwwicylymmx00xkub00bz9mkle", "appData": {"ToolsClicked": "[\"Equal Sides tool\",\"Parallel Lines tool\",\"Equal Sides tool\",\"Equal Sides tool\",\"Right Angle tool\"]", "MissionsCompleted": [0, 0, 0, 0], "CorrectRelease": "[]", "CurrentLevel": "", "CaseDetails": ["exactly3emptysides", ["fig001", "fig070", "fig054", "fig063", null, null, null, null], ["The culprit has less than 5 straight sides"], ["Incorrect"]], "scoreAchieved": 30, "GlossaryDownloaded": false, "MissionsPlayed": [1, 0, 0, 0], "starEarned": 0, "HyperlinksClicked": "[\"straight sides\"]", "StagePlayed": 1, "ReplayUsedNumber": 0, "NumberOfErrors": "", "NumberOfClues": "", "starTotal": 0, "IncorrectRelease": "[{\"clue\":1,\"fig\":[\"fig001\",\"fig070\",\"fig063\"]}]", "statusConpleted": "failed", "StorySkiped": true, "highScore": 30, "CurrentMission": "Mission 1", "TimeSpentStage": "0:0:53"}, "buddyIds": "", "createdAt": "2018-10-30 12:45:29"}, {"event_type": "stage_end", "appData": {"ToolsClicked": "[]", "MissionsCompleted": [0, 0, 0, 0], "CurrentLevel": "", "CurrentMission": "Mission 1", "CaseDetails": ["exactly2equalpairsofsides", ["fig060", "fig047", "fig013", "fig066", null, null, null, null], ["The culprit has no curved sides"], ["Incorrect"]], "scoreAchieved": 30, "GlossaryDownloaded": false, "MissionsPlayed": [1, 0, 0, 0], "starEarned": 0, "NumberOfClues": "", "StagePlayed": 1, "ReplayUsedNumber": 0, "CorrectRelease": "[]", "TimeSpentStage": "0:0:24", "starTotal": 0, "IncorrectRelease": "[{\"clue\":1,\"fig\":[\"fig060\",\"fig047\",\"fig066\"]}]", "statusConpleted": "failed", "StorySkiped": true, "highScore": 30, "HyperlinksClicked": "[\"curved sides\"]", "NumberOfErrors": ""}, "appName": "policesquad", "userId": "28372", "language": "en", "sessionId": "xuj375mwwicylymmx00xkub00bz9mkle", "buddyIds": "", "createdAt": "2018-10-30 12:45:54"}, {"event_type": "stage_end", "language": "en", "appName": "policesquad", "userId": "28372", "sessionId": "xuj375mwwicylymmx00xkub00bz9mkle", "appData": {"ToolsClicked": "[]", "MissionsCompleted": [0, 0, 0, 0], "CorrectRelease": "[]", "CurrentLevel": "", "CaseDetails": ["exactly3equalpairsofsides", ["fig010", "fig052", "fig049", "fig045", null, null, null, null], ["The culprit has exactly 6 straight sides"], ["Incorrect"]], "scoreAchieved": 30, "GlossaryDownloaded": false, "MissionsPlayed": [1, 0, 0, 0], "starEarned": 0, "HyperlinksClicked": "[\"straight sides\"]", "StagePlayed": 1, "ReplayUsedNumber": 0, "NumberOfErrors": "", "NumberOfClues": "", "starTotal": 0, "IncorrectRelease": "[{\"clue\":1,\"fig\":[\"fig010\",\"fig052\",\"fig045\"]}]", "statusConpleted": "passed", "StorySkiped": true, "highScore": 30, "CurrentMission": "Mission 1", "TimeSpentStage": "0:0:35"}, "buddyIds": "", "createdAt": "2018-10-30 12:46:29"}, {"event_type": "stage_end", "appData": {"ToolsClicked": "[]", "MissionsCompleted": [0, 0, 0, 0], "CurrentLevel": "", "CurrentMission": "Mission 1", "CaseDetails": ["all1equalsides", ["fig038", "fig030", "fig054", "fig053", null, null, null, null], ["The culprit has more than 6 straight sides"], ["Incorrect"]], "scoreAchieved": 30, "GlossaryDownloaded": false, "MissionsPlayed": [1, 0, 0, 0], "starEarned": 0, "NumberOfClues": "", "StagePlayed": 2, "ReplayUsedNumber": 0, "CorrectRelease": "[]", "TimeSpentStage": "0:0:13", "starTotal": 0, "IncorrectRelease": "[{\"clue\":1,\"fig\":[\"fig038\",\"fig030\",\"fig053\"]}]", "statusConpleted": "failed", "StorySkiped": true, "highScore": 30, "HyperlinksClicked": "[]", "NumberOfErrors": ""}, "appName": "policesquad", "userId": "28372", "language": "en", "sessionId": "xuj375mwwicylymmx00xkub00bz9mkle", "buddyIds": "", "createdAt": "2018-10-30 12:46:43"}, {"event_type": "stage_end", "language": "en", "appName": "policesquad", "userId": "28372", "sessionId": "xuj375mwwicylymmx00xkub00bz9mkle", "appData": {"ToolsClicked": "[]", "MissionsCompleted": [0, 0, 0, 0], "CorrectRelease": "[]", "CurrentLevel": "", "CaseDetails": ["no1equalpairsofsides", ["fig025", "fig012", "fig032", "fig033", null, null, null, null], ["The culprit has less than 4 right angles"], ["Incorrect"]], "scoreAchieved": 30, "GlossaryDownloaded": false, "MissionsPlayed": [1, 0, 0, 0], "starEarned": 0, "HyperlinksClicked": "[]", "StagePlayed": 2, "ReplayUsedNumber": 0, "NumberOfErrors": "", "NumberOfClues": "", "starTotal": 0, "IncorrectRelease": "[{\"clue\":1,\"fig\":[\"fig025\",\"fig012\",\"fig033\"]}]", "statusConpleted": "failed", "StorySkiped": true, "highScore": 30, "CurrentMission": "Mission 1", "TimeSpentStage": "0:0:27"}, "buddyIds": "", "createdAt": "2018-10-30 12:47:11"}, {"event_type": "stage_end", "appData": {"ToolsClicked": "[]", "MissionsCompleted": [0, 0, 0, 0], "CurrentLevel": "", "CurrentMission": "Mission 1", "CaseDetails": ["all1equalsides", ["fig010", "fig049", "fig061", "fig015", null, null, null, null], ["The culprit has exactly 4 straight sides"], ["Incorrect"]], "scoreAchieved": 30, "GlossaryDownloaded": false, "MissionsPlayed": [1, 0, 0, 0], "starEarned": 0, "NumberOfClues": "", "StagePlayed": 2, "ReplayUsedNumber": 0, "CorrectRelease": "[]", "TimeSpentStage": "0:0:28", "starTotal": 0, "IncorrectRelease": "[{\"clue\":1,\"fig\":[\"fig049\",\"fig061\",\"fig015\"]}]", "statusConpleted": "failed", "StorySkiped": true, "highScore": 30, "HyperlinksClicked": "[]", "NumberOfErrors": ""}, "appName": "policesquad", "userId": "28372", "language": "en", "sessionId": "xuj375mwwicylymmx00xkub00bz9mkle", "buddyIds": "", "createdAt": "2018-10-30 12:47:40"}, {"event_type": "stage_end", "language": "en", "appName": "policesquad", "userId": "28372", "sessionId": "xuj375mwwicylymmx00xkub00bz9mkle", "appData": {"ToolsClicked": "[\"Right Angle tool\"]", "MissionsCompleted": [0, 0, 0, 0], "CorrectRelease": "[]", "CurrentLevel": "", "CaseDetails": ["no1rightangles", ["fig004", "fig011", "fig046", "fig003", null, null, null, null], ["The culprit has less than 2 equal pairs of sides ", "The culprit has less than 2 right angles"], ["", "Incorrect"]], "scoreAchieved": 20, "GlossaryDownloaded": false, "MissionsPlayed": [1, 0, 0, 0], "starEarned": 0, "HyperlinksClicked": "[]", "StagePlayed": 2, "ReplayUsedNumber": 3, "NumberOfErrors": "", "NumberOfClues": "", "starTotal": 0, "IncorrectRelease": "[{\"clue\":1,\"fig\":[\"fig004\",\"fig046\",\"fig003\"]}]", "statusConpleted": "failed", "StorySkiped": true, "highScore": 30, "CurrentMission": "Mission 1", "TimeSpentStage": "0:2:17"}, "buddyIds": "", "createdAt": "2018-10-30 12:53:3"}, {"event_type": "stage_end", "appData": {"ToolsClicked": "[\"Right Angle tool\"]", "MissionsCompleted": [0, 0, 0, 0], "CurrentLevel": "", "CurrentMission": "Mission 1", "CaseDetails": ["all1rightangles", ["fig059", "fig060", "fig054", "fig035", null, null, null, null], ["The culprit has more than 1 equal pairs of sides ", "The culprit has atleast 2 right angles", "The culprit has more than 1 right angle"], ["", "Incorrect", "Incorrect"]], "scoreAchieved": 20, "GlossaryDownloaded": false, "MissionsPlayed": [1, 0, 0, 0], "starEarned": 0, "NumberOfClues": "", "StagePlayed": 2, "ReplayUsedNumber": 3, "CorrectRelease": "[]", "TimeSpentStage": "0:1:27", "starTotal": 0, "IncorrectRelease": "[{\"clue\":1,\"fig\":[\"fig059\"]},{\"clue\":2,\"fig\":[\"fig060\",\"fig054\"]}]", "statusConpleted": "failed", "StorySkiped": true, "highScore": 30, "HyperlinksClicked": "[\"right angles\"]", "NumberOfErrors": ""}, "appName": "policesquad", "userId": "28372", "language": "en", "sessionId": "xuj375mwwicylymmx00xkub00bz9mkle", "buddyIds": "", "createdAt": "2018-10-30 12:54:30"}, {"event_type": "stage_end", "language": "en", "appName": "policesquad", "userId": "28372", "sessionId": "xuj375mwwicylymmx00xkub00bz9mkle", "appData": {"ToolsClicked": "[]", "MissionsCompleted": [0, 0, 0, 0], "CorrectRelease": "[]", "CurrentLevel": "", "CaseDetails": ["all1equalsides", ["fig025", "fig026", "fig035", "fig057", null, null, null, null], ["The culprit has atleast 2 right angles", "The culprit has more than 1 right angle", "The culprit has more than 2 right angles"], ["Incorrect", "Incorrect", "Incorrect"]], "scoreAchieved": 10, "GlossaryDownloaded": false, "MissionsPlayed": [1, 0, 0, 0], "starEarned": 0, "HyperlinksClicked": "[]", "StagePlayed": 2, "ReplayUsedNumber": 3, "NumberOfErrors": "", "NumberOfClues": "", "starTotal": 0, "IncorrectRelease": "[{\"clue\":1,\"fig\":[\"fig025\"]},{\"clue\":2,\"fig\":[\"fig026\"]},{\"clue\":3,\"fig\":[\"fig035\"]}]", "statusConpleted": "failed", "StorySkiped": true, "highScore": 30, "CurrentMission": "Mission 1", "TimeSpentStage": "0:0:42"}, "buddyIds": "", "createdAt": "2018-10-30 12:55:13"}, {"event_type": "stage_end", "appData": {"ToolsClicked": "[]", "MissionsCompleted": [0, 0, 0, 0], "CurrentLevel": "", "CurrentMission": "Mission 1", "CaseDetails": ["no1equalpairsofsides", ["fig056", "fig042", "fig039", "fig040", null, null, null, null], ["The culprit has less than 3 equal pairs of sides "], ["Incorrect"]], "scoreAchieved": 30, "GlossaryDownloaded": false, "MissionsPlayed": [1, 0, 0, 0], "starEarned": 0, "NumberOfClues": "", "StagePlayed": 2, "ReplayUsedNumber": 3, "CorrectRelease": "[]", "TimeSpentStage": "0:0:12", "starTotal": 0, "IncorrectRelease": "[{\"clue\":1,\"fig\":[\"fig042\",\"fig039\",\"fig040\"]}]", "statusConpleted": "failed", "StorySkiped": true, "highScore": 30, "HyperlinksClicked": "[]", "NumberOfErrors": ""}, "appName": "policesquad", "userId": "28372", "language": "en", "sessionId": "xuj375mwwicylymmx00xkub00bz9mkle", "buddyIds": "", "createdAt": "2018-10-30 12:55:26"}, {"event_type": "stage_end", "language": "en", "appName": "policesquad", "userId": "28372", "sessionId": "xuj375mwwicylymmx00xkub00bz9mkle", "appData": {"ToolsClicked": "[]", "MissionsCompleted": [0, 0, 0, 0], "CorrectRelease": "[]", "CurrentLevel": "", "CaseDetails": ["all1equalsides", ["fig053", "fig057", "fig007", "fig054", null, null, null, null], ["The culprit has less than 2 right angles"], ["Incorrect"]], "scoreAchieved": 20, "GlossaryDownloaded": false, "MissionsPlayed": [1, 0, 0, 0], "starEarned": 0, "HyperlinksClicked": "[]", "StagePlayed": 2, "ReplayUsedNumber": 18, "NumberOfErrors": "", "NumberOfClues": "", "starTotal": 0, "IncorrectRelease": "[{\"clue\":1,\"fig\":[\"fig053\",\"fig007\",\"fig054\"]}]", "statusConpleted": "failed", "StorySkiped": true, "highScore": 30, "CurrentMission": "Mission 1", "TimeSpentStage": "0:0:18"}, "buddyIds": "", "createdAt": "2018-10-30 12:56:12"}, {"event_type": "stage_end", "appData": {"ToolsClicked": "[]", "MissionsCompleted": [0, 0, 0, 0], "CurrentLevel": "", "CurrentMission": "Mission 1", "CaseDetails": ["no1equalpairsofsides", ["fig038", "fig050", "fig011", "fig022", null, null, null, null], ["The culprit has less than 2 right angles", "The culprit has less than 6 straight sides"], ["Incorrect", "Correct"]], "scoreAchieved": 30, "GlossaryDownloaded": false, "MissionsPlayed": [1, 0, 0, 0], "starEarned": 0, "NumberOfClues": "", "StagePlayed": 2, "ReplayUsedNumber": 18, "CorrectRelease": "[{\"clue\":1,\"fig\":[\"fig050\"]}]", "TimeSpentStage": "0:0:56", "starTotal": 0, "IncorrectRelease": "[{\"clue\":2,\"fig\":[\"fig022\"]}]", "statusConpleted": "failed", "StorySkiped": true, "highScore": 30, "HyperlinksClicked": "[]", "NumberOfErrors": ""}, "appName": "policesquad", "userId": "28372", "language": "en", "sessionId": "xuj375mwwicylymmx00xkub00bz9mkle", "buddyIds": "", "createdAt": "2018-10-30 12:57:8"}, {"event_type": "stage_end", "language": "en", "appName": "policesquad", "userId": "28372", "sessionId": "xuj375mwwicylymmx00xkub00bz9mkle", "appData": {"ToolsClicked": "[]", "MissionsCompleted": [0, 0, 0, 0], "CorrectRelease": "[{\"clue\":1,\"fig\":[\"fig002\"]}]", "CurrentLevel": "", "CaseDetails": ["all1rightangles", ["fig002", "fig037", "fig059", "fig032", null, null, null, null], ["The culprit has atleast 2 right angles", "The culprit has more than 1 equal pairs of sides "], ["Incorrect", "Correct"]], "scoreAchieved": 30, "GlossaryDownloaded": false, "MissionsPlayed": [1, 0, 0, 0], "starEarned": 0, "HyperlinksClicked": "[]", "StagePlayed": 2, "ReplayUsedNumber": 18, "NumberOfErrors": "", "NumberOfClues": "", "starTotal": 0, "IncorrectRelease": "[{\"clue\":2,\"fig\":[\"fig037\",\"fig032\"]}]", "statusConpleted": "passed", "StorySkiped": true, "highScore": 30, "CurrentMission": "Mission 1", "TimeSpentStage": "0:1:4"}, "buddyIds": "", "createdAt": "2018-10-30 12:58:13"}, {"event_type": "stage_end", "appData": {"ToolsClicked": "[]", "MissionsCompleted": [0, 0, 0, 0], "CurrentLevel": "", "CurrentMission": "Mission 1", "CaseDetails": ["exactly3rightangles", ["fig021", "fig041", "fig069", "fig039", null, null, null, null], ["The culprit has atleast 1 right angle", "The culprit has no curved sides"], ["Incorrect", "Incorrect"]], "scoreAchieved": 20, "GlossaryDownloaded": false, "MissionsPlayed": [1, 0, 0, 0], "starEarned": 0, "NumberOfClues": "", "StagePlayed": 3, "ReplayUsedNumber": 18, "CorrectRelease": "[]", "TimeSpentStage": "0:0:33", "starTotal": 0, "IncorrectRelease": "[{\"clue\":1,\"fig\":[\"fig021\"]},{\"clue\":2,\"fig\":[\"fig041\",\"fig039\"]}]", "statusConpleted": "failed", "StorySkiped": true, "highScore": 30, "HyperlinksClicked": "[]", "NumberOfErrors": ""}, "appName": "policesquad", "userId": "28372", "language": "en", "sessionId": "xuj375mwwicylymmx00xkub00bz9mkle", "buddyIds": "", "createdAt": "2018-10-30 12:58:46"}, {"event_type": "stage_end", "language": "en", "appName": "policesquad", "userId": "28372", "sessionId": "xuj375mwwicylymmx00xkub00bz9mkle", "appData": {"ToolsClicked": "[]", "MissionsCompleted": [0, 0, 0, 0], "CorrectRelease": "[]", "CurrentLevel": "", "CaseDetails": ["exactly3rightangles", ["fig032", "fig033", "fig047", "fig008", null, null, null, null], ["The culprit has atleast 1 right angle", "The culprit has more than 4 straight sides"], ["Incorrect", "Incorrect"]], "scoreAchieved": 20, "GlossaryDownloaded": false, "MissionsPlayed": [1, 0, 0, 0], "starEarned": 0, "HyperlinksClicked": "[]", "StagePlayed": 3, "ReplayUsedNumber": 18, "NumberOfErrors": "", "NumberOfClues": "", "starTotal": 0, "IncorrectRelease": "[{\"clue\":1,\"fig\":[\"fig032\"]},{\"clue\":2,\"fig\":[\"fig047\",\"fig008\"]}]", "statusConpleted": "failed", "StorySkiped": true, "highScore": 30, "CurrentMission": "Mission 1", "TimeSpentStage": "0:0:43"}, "buddyIds": "", "createdAt": "2018-10-30 12:59:30"}, {"event_type": "stage_end", "appData": {"ToolsClicked": "[]", "MissionsCompleted": [0, 0, 0, 0], "CurrentLevel": "", "CurrentMission": "Mission 1", "CaseDetails": ["exactly4rightangles", ["fig060", "fig059", "fig046", "fig048", null, null, null, null], ["The culprit has less than 5 straight sides", "The culprit has atleast 1 right angle", "The culprit has less than 6 straight sides"], ["Correct", "Incorrect", "Incorrect"]], "scoreAchieved": 20, "GlossaryDownloaded": false, "MissionsPlayed": [1, 0, 0, 0], "starEarned": 0, "NumberOfClues": "", "StagePlayed": 3, "ReplayUsedNumber": 18, "CorrectRelease": "[{\"clue\":3,\"fig\":[\"fig048\"]}]", "TimeSpentStage": "0:0:38", "starTotal": 0, "IncorrectRelease": "[{\"clue\":1,\"fig\":[\"fig060\"]},{\"clue\":2,\"fig\":[\"fig046\"]}]", "statusConpleted": "passed", "StorySkiped": true, "highScore": 30, "HyperlinksClicked": "[]", "NumberOfErrors": ""}, "appName": "policesquad", "userId": "28372", "language": "en", "sessionId": "xuj375mwwicylymmx00xkub00bz9mkle", "buddyIds": "", "createdAt": "2018-10-30 13:0:8"}, {"event_type": "stage_end", "language": "en", "appName": "policesquad", "userId": "28372", "sessionId": "xuj375mwwicylymmx00xkub00bz9mkle", "appData": {"ToolsClicked": "[\"Right Angle tool\",\"Right Angle tool\",\"Right Angle tool\",\"Right Angle tool\",\"Equal Sides tool\",\"Right Angle tool\",\"Equal Sides tool\"]", "MissionsCompleted": [0, 0, 0, 0], "scoreAchieved": 100, "CurrentLevel": "", "CaseDetails": ["exactly1obtuseangles", ["fig016", "fig022", "fig009", "fig054", "fig033", "fig042", null, null], ["The culprit has no equal straight sides", "The culprit has atleast 1 right angle", "The culprit has less than 2 equal pairs of sides ", "The culprit has atleast 1 obtuse angle"], ["Correct", "Correct", "Correct", "Correct"]], "CorrectRelease": "[{\"clue\":1,\"fig\":[\"fig009\",\"fig054\"]},{\"clue\":2,\"fig\":[\"fig042\"]},{\"clue\":3,\"fig\":[\"fig022\"]},{\"clue\":4,\"fig\":[\"fig016\"]}]", "GlossaryDownloaded": false, "MissionsPlayed": [1, 0, 0, 0], "starEarned": 0, "highScore": 100, "HyperlinksClicked": "[\"obtuse angle\",\"obtuse angle\",\"obtuse angle\",\"obtuse angle\",\"obtuse angle\",\"obtuse angle\",\"equal pairs of sides\"]", "StagePlayed": 4, "ReplayUsedNumber": 30, "NumberOfClues": "", "starTotal": 0, "IncorrectRelease": "[{\"clue\":1,\"fig\":[\"fig022\"]},{\"clue\":1,\"fig\":[\"fig054\",\"fig016\",\"fig033\"]},{\"clue\":1,\"fig\":[\"fig016\"]},{\"clue\":1,\"fig\":[\"fig042\"]},{\"clue\":1,\"fig\":[\"fig022\"]},{\"clue\":1,\"fig\":[\"fig042\"]},{\"clue\":1,\"fig\":[\"fig016\"]},{\"clue\":1,\"fig\":[\"fig009\"]},{\"clue\":1,\"fig\":[\"fig022\"]}]", "statusConpleted": "passed", "StorySkiped": true, "NumberOfErrors": "", "CurrentMission": "Mission 1", "TimeSpentStage": "0:9:19"}, "buddyIds": "", "createdAt": "2018-10-30 13:15:17"}]