{
	"clix_variables_config_schooldb": {
		"mz": {
		"syncInfo_0": {
			"date": "2019-10-13",
			"schools": []
    },
		"schools_synced_so_far":[]
	},

	"ts": {
"syncInfo_0": {
			"date": "2019-10-13",
			"schools": []
    },
		"schools_synced_so_far":[]

	},

	"cg": {
"syncInfo_0": {
			"date": "2019-10-13",
			"schools": []
    },
		"schools_synced_so_far":[]
	},

	"rj":{
"syncInfo_0": {
			"date": "2019-10-13",
			"schools": []
    },
		"schools_synced_so_far":[]
	}
	},

	"clix_variables_config_static_vis": {
		"syncInfo_0": {
			"date": "2019-10-13",
			"schools": []
		}
	},

	"static_vis_range": {
		"months_list": ["all_months", "Jul2018", "Aug2018", "Sep2018", "Oct2018", "Nov2018",
			"Dec2018", "Jan2019", "Feb2019", "Mar2019", "Apr2019", "May2019", "Jun2019",
			"Jul2019", "Aug2019", "Sep2019", "Oct2019"]
	},

  "prev_update_date_mz": "2018-07-01",

  "prev_update_date_ct": "2018-07-01",

  "prev_update_date_tg": "2018-07-01",

  "prev_update_date_rj": "2018-07-01",

	"curr_update_date_mz": "2019-11-14",

  "curr_update_date_ct": "2019-11-14",

  "curr_update_date_tg": "2019-11-14",

  "curr_update_date_rj": "2019-11-14",

	"prev_update_date_static_mz": "2018-07-01",

  "prev_update_date_static_ct": "2018-07-01",

  "prev_update_date_static_tg": "2018-07-01",

  "prev_update_date_static_rj": "2018-07-01",

	"curr_update_date_static_mz": "2019-11-14",

  "curr_update_date_static_ct": "2019-11-14",

  "curr_update_date_static_tg": "2019-11-14",

  "curr_update_date_static_rj": "2019-11-14"

}
